thor_mlops/__init__.py
thor_mlops/clean.py
thor_mlops/ops.py
thor_mlops/starschema.py
thor_mlops-0.0.1.dist-info/LICENSE
thor_mlops-0.0.1.dist-info/METADATA
thor_mlops-0.0.1.dist-info/WHEEL
thor_mlops-0.0.1.dist-info/top_level.txt
thor_mlops-0.0.1.dist-info/RECORD
