Metadata-Version: 2.1
Name: thor-mlops
Version: 0.0.1
Summary: Amazing ML ops for preprocessing, feature storage and inference
Author-email: Tom Scheffers <tom@thunderstock.nl>
License: Apache License
Project-URL: Homepage, https://github.com/TomScheffers/thor-mlops
Keywords: ml,pyarrow,preprocessing
License-File: LICENSE
Requires-Dist: pyarrow (>=8.0.0)
